{
    "ca": {
        "1": {
            "appealsuit": {
                "header": [
                    "Sl.No.",
                    "Description of Document",
                    "Date of Document",
                    "Date of filing of Document",
                    "Page No."
                ],
                "headerbold": false,
                "rows": [
                    {
                        "Sl_No": "1",
                        "Description_of_Document": "",
                        "Date_of_Document": "",
                        "Date_of_filing_of_Document": "",
                        "Page_No": ""
                    },
                    {
                        "Sl_No": "2",
                        "Description_of_Document": "",
                        "Date_of_Document": "",
                        "Date_of_filing_of_Document": "",
                        "Page_No": ""
                    },
                    {
                        "Sl_No": "3",
                        "Description_of_Document": "",
                        "Date_of_Document": "",
                        "Date_of_filing_of_Document": "",
                        "Page_No": ""
                    },
                    {
                        "Sl_No": "4",
                        "Description_of_Document": "",
                        "Date_of_Document": "",
                        "Date_of_filing_of_Document": "",
                        "Page_No": ""
                    },
                    {
                        "Sl_No": "5",
                        "Description_of_Document": "",
                        "Date_of_Document": "",
                        "Date_of_filing_of_Document": "",
                        "Page_No": ""
                    }
                ]
            }
        }
    }
}